{
  "users": [
    {
      "id": 114945935223681152221,
      "name": "홍승표[학생](소프트웨어융합대학 컴퓨터공학부)",
      "email": "zackinthebox@khu.ac.kr",
      "photoUrl": null,
      "serverAuthCode": null,
      "win": 0,
      "lose": 0,
      "tier": "unRanked",
      "tierPoint": 0,
      "friend": []
    }
  ],
  "games": [
    {
      "id": 1234,
      "host": 114945935223681152221,
      "visitor": 114945935223681152221,
      "when": "2024-07-08-15-20",
      "win": 114945935223681152221,
      "lose": 114945935223681152221,
      "isRank": false
    }
  ]
}
